multi_domains/__init__.py
multi_domains/middleware.py
django_multi_domains-0.0.1.dist-info/LICENSE
django_multi_domains-0.0.1.dist-info/METADATA
django_multi_domains-0.0.1.dist-info/WHEEL
django_multi_domains-0.0.1.dist-info/top_level.txt
django_multi_domains-0.0.1.dist-info/RECORD
